hospytal/__init__.py
hospytal/scrap.py
hospytal/xgoogle/BeautifulSoup.py
hospytal/xgoogle/__init__.py
hospytal/xgoogle/browser.py
hospytal/xgoogle/example1.py
hospytal/xgoogle/example2.py
hospytal/xgoogle/example3.py
hospytal/xgoogle/googlesets.py
hospytal/xgoogle/search.py
hospytal/xgoogle/sponsoredlinks.py
hospytal/xgoogle/translate.py
hospytal-0.0.4.dist-info/LICENSE
hospytal-0.0.4.dist-info/METADATA
hospytal-0.0.4.dist-info/WHEEL
hospytal-0.0.4.dist-info/top_level.txt
hospytal-0.0.4.dist-info/RECORD
