Metadata-Version: 2.1
Name: hospytal
Version: 0.0.4
Summary: A medley of stuff that could be useful if and when repaired
Home-page: https://github.com/thorwhalen/ut/tree/master/hospytal
Author: Thor Whalen
License: mit
Platform: any
